{
  "main": {
    "id": "4f48d574257473d6",
    "type": "split",
    "children": [
      {
        "id": "4a5f28d7f3efca33",
        "type": "tabs",
        "children": [
          {
            "id": "43d92b5d97b940cf",
            "type": "leaf",
            "state": {
              "type": "markdown",
              "state": {
                "file": "证书笔记/PMP/错题集/第十一章 项目风险管理.md",
                "mode": "source",
                "source": false
              }
            }
          },
          {
            "id": "c0101c1bff6a5fcf",
            "type": "leaf",
            "state": {
              "type": "markdown",
              "state": {
                "file": "日记记录/2023-03-24_周五.md",
                "mode": "source",
                "source": false
              }
            }
          },
          {
            "id": "3bdfb2006ab62c7f",
            "type": "leaf",
            "state": {
              "type": "markdown",
              "state": {
                "file": "证书笔记/PMP/错题集/第十三章 项目相关方管理.md",
                "mode": "source",
                "source": false
              }
            }
          }
        ],
        "currentTab": 2
      }
    ],
    "direction": "vertical"
  },
  "left": {
    "id": "20b3500cc219be57",
    "type": "split",
    "children": [
      {
        "id": "33b59a9dbd3c3383",
        "type": "tabs",
        "children": [
          {
            "id": "fa8e25a3ff5b0cd6",
            "type": "leaf",
            "state": {
              "type": "recent-files",
              "state": {}
            }
          },
          {
            "id": "afbb7091c5974add",
            "type": "leaf",
            "state": {
              "type": "file-explorer",
              "state": {
                "sortOrder": "custom"
              }
            }
          },
          {
            "id": "ae9ff347ef7bd118",
            "type": "leaf",
            "state": {
              "type": "search",
              "state": {
                "query": "tag:#PMO",
                "matchingCase": false,
                "explainSearch": false,
                "collapseAll": false,
                "extraContext": false,
                "sortOrder": "alphabetical"
              }
            }
          },
          {
            "id": "b644b9022d95006e",
            "type": "leaf",
            "state": {
              "type": "starred",
              "state": {}
            }
          },
          {
            "id": "17e40c0a97a737fc",
            "type": "leaf",
            "state": {
              "type": "surfing-tab-tree",
              "state": {}
            }
          }
        ],
        "currentTab": 1
      }
    ],
    "direction": "horizontal",
    "width": 299.5
  },
  "right": {
    "id": "72d7cd9c0ddcff48",
    "type": "split",
    "children": [
      {
        "id": "f2d5408196d03ae4",
        "type": "tabs",
        "children": [
          {
            "id": "9419f04e15a5a4cf",
            "type": "leaf",
            "state": {
              "type": "calendar",
              "state": {}
            }
          },
          {
            "id": "9dafad2df68a9719",
            "type": "leaf",
            "state": {
              "type": "backlink",
              "state": {
                "file": "证书笔记/PMP/错题集/第十三章 项目相关方管理.md",
                "collapseAll": false,
                "extraContext": false,
                "sortOrder": "alphabetical",
                "showSearch": false,
                "searchQuery": "",
                "backlinkCollapsed": false,
                "unlinkedCollapsed": true
              }
            }
          },
          {
            "id": "fbf1d085e2bfc724",
            "type": "leaf",
            "state": {
              "type": "tag",
              "state": {
                "sortOrder": "frequency",
                "useHierarchy": true
              }
            }
          },
          {
            "id": "0c35527b83481898",
            "type": "leaf",
            "state": {
              "type": "outline",
              "state": {
                "file": "证书笔记/PMP/错题集/第十三章 项目相关方管理.md"
              }
            }
          },
          {
            "id": "e9336c15d3339dbd",
            "type": "leaf",
            "state": {
              "type": "advanced-tables-toolbar",
              "state": {}
            }
          },
          {
            "id": "1fef502238e5f466",
            "type": "leaf",
            "state": {
              "type": "todo",
              "state": {}
            }
          }
        ]
      },
      {
        "id": "16101ca95a767e19",
        "type": "tabs",
        "children": [
          {
            "id": "0584f423966c4f2e",
            "type": "leaf",
            "state": {
              "type": "timeline",
              "state": {}
            }
          }
        ]
      }
    ],
    "direction": "horizontal",
    "width": 395.5
  },
  "left-ribbon": {
    "hiddenItems": {
      "canvas:新建白板": false,
      "switcher:打开快速切换": false,
      "graph:查看关系图谱": false,
      "daily-notes:打开/创建今天的日记": false,
      "command-palette:打开命令面板": false,
      "markdown-importer:打开 Markdown 格式转换器": false,
      "audio-recorder:开始/结束录音": false,
      "workspaces:管理工作区布局": false,
      "privacy-glasses:Hide all": false,
      "table-editor-obsidian:Advanced Tables Toolbar": false,
      "privacy-glasses:Reveal non-private": false,
      "privacy-glasses:Reveal all": false,
      "templater-obsidian:Templater": false,
      "obsidian-excalidraw-plugin:新建 Excalidraw 绘图": false
    }
  },
  "active": "3bdfb2006ab62c7f",
  "lastOpenFiles": [
    "垃圾袋/1679668207352.png",
    "日记记录/2023-03-24_周五.md",
    "证书笔记/PMP/错题集/第十三章 项目相关方管理.md",
    "日记记录/2023-03-23_周四.md",
    "证书笔记/PMP/错题集/第十二章 项目采购管理.md",
    "垃圾袋/Pasted image 20230323220449.png",
    "证书笔记/PMP/错题集/第十一章 项目风险管理.md",
    "日记记录/2023-03-20_周一.md",
    "日记记录/2023-03-21_周二.md",
    "日记记录/2023-03-22_周三.md",
    "2023年上半年规划.md",
    "垃圾袋/Pasted image 20230321220523.png",
    "垃圾袋/Pasted image 20230321220228.png",
    "证书笔记/PMP/错题集/第十一章.md",
    "四月旅行路线.md",
    "证书笔记/PMP/错题集/第十章 项目沟通管理.md",
    "证书笔记/PMP/错题集/第九章 项目资源管理.md",
    "证书笔记/PMP/错题集/第八章 项目质量管理.md",
    "垃圾袋/dc950b8824327e4d58abcc45147c570.jpg",
    "垃圾袋/a3cb4e0d5ca81e1806112a3d6b6e005.jpg",
    "垃圾袋/Pasted image 20230319125105.png",
    "垃圾袋/Pasted image 20230319124958.png",
    "垃圾袋/Pasted image 20230319093402.png",
    "垃圾袋/Pasted image 20230319093137.png",
    "垃圾袋/Pasted image 20230319092533.png",
    "视频笔记/纪录片/河西走廊.md",
    "日记记录/202303/2023-03-01_周三.md",
    "日记记录/202303/2023-03-17_周五.md",
    "日记记录/202303",
    "日记记录/202303/2023-03-16_周四.md",
    "日记记录/202303/2023-03-15_周三.md",
    "知识库/Python/数据分析/数据分析学习内容.md",
    "日记记录/202303/2023-03-14_周二.md",
    "日记记录/202303/2023-03-13_周一.md",
    "证书笔记/PMP/错题集/第七章 项目成本管理.md",
    "视频笔记/纪录片.md",
    "李狗蛋喜好.md",
    "视频笔记/纪录片",
    "视频笔记",
    "读书笔记/艺术",
    "读书笔记/人物传记",
    "读书笔记/漫画",
    "读书笔记/精品小说",
    "读书笔记/社会文化",
    "读书笔记/政治军事",
    "读书笔记/科学技术"
  ]
}